gEconpy/__init__.py
gEconpy/_version.py
gEconpy/dynare_convert.py
gEconpy/exceptions.py
gEconpy/plotting.py
gEconpy/utilities.py
gEconpy/classes/__init__.py
gEconpy/classes/containers.py
gEconpy/classes/time_aware_symbol.py
gEconpy/model/__init__.py
gEconpy/model/block.py
gEconpy/model/build.py
gEconpy/model/compile.py
gEconpy/model/model.py
gEconpy/model/parameters.py
gEconpy/model/perturbation.py
gEconpy/model/simplification.py
gEconpy/model/statespace.py
gEconpy/model/steady_state.py
gEconpy/numbaf/LAPACK.py
gEconpy/numbaf/__init__.py
gEconpy/numbaf/intrinsics.py
gEconpy/numbaf/overloads.py
gEconpy/numbaf/utilities.py
gEconpy/parser/__init__.py
gEconpy/parser/constants.py
gEconpy/parser/dist_syntax.py
gEconpy/parser/file_loaders.py
gEconpy/parser/gEcon_parser.py
gEconpy/parser/html.py
gEconpy/parser/parse_distributions.py
gEconpy/parser/parse_equations.py
gEconpy/parser/parse_plaintext.py
gEconpy/parser/validation.py
gEconpy/solvers/__init__.py
gEconpy/solvers/cycle_reduction.py
gEconpy/solvers/gensys.py
gEconpy/solvers/shared.py
geconpy-2.0.3.dist-info/METADATA
geconpy-2.0.3.dist-info/WHEEL
geconpy-2.0.3.dist-info/licenses/LICENSE
geconpy-2.0.3.dist-info/RECORD
