Metadata-Version: 2.4
Name: gEconpy
Version: 2.0.3
Summary: A package for solving, estimating, and analyzing DSGE models
Author-email: Jesse Grabowski <jessegrabowski@gmail.com>
License:                     GNU GENERAL PUBLIC LICENSE
License-File: LICENSE
Keywords: autodiff,bayesian statistics,dynamic stochastic general equlibrium,economics,macroeconomics,numerical,simulation
Classifier: Development Status :: 2 - Pre-Alpha
Classifier: Intended Audience :: Science/Research
Classifier: Operating System :: MacOS
Classifier: Operating System :: Microsoft :: Windows
Classifier: Operating System :: POSIX
Classifier: Operating System :: Unix
Classifier: Programming Language :: Python
Classifier: Programming Language :: Python :: 3
Classifier: Programming Language :: Python :: 3.10
Classifier: Programming Language :: Python :: 3.11
Classifier: Programming Language :: Python :: 3.12
Classifier: Topic :: Scientific/Engineering
Requires-Python: >=3.11
Requires-Dist: ipython
Requires-Dist: matplotlib
Requires-Dist: numba
Requires-Dist: numpy
Requires-Dist: pandas
Requires-Dist: preliz>=0.2.0
Requires-Dist: pymc-extras>=0.4.0
Requires-Dist: pymc>=5.25.0
Requires-Dist: pyparsing
Requires-Dist: pytensor
Requires-Dist: scipy
Requires-Dist: setuptools
Requires-Dist: sympy>=1.14.0
Requires-Dist: sympytensor
Requires-Dist: xarray
Provides-Extra: dev
Requires-Dist: numdifftools; extra == 'dev'
Requires-Dist: pre-commit; extra == 'dev'
Requires-Dist: pytest; extra == 'dev'
Requires-Dist: pytest-cov; extra == 'dev'
Requires-Dist: versioneer; extra == 'dev'
Provides-Extra: docs
Requires-Dist: ipython; extra == 'docs'
Requires-Dist: jupyter-sphinx; extra == 'docs'
Requires-Dist: myst-nb; extra == 'docs'
Requires-Dist: numpydoc; extra == 'docs'
Requires-Dist: pre-commit; extra == 'docs'
Requires-Dist: pydata-sphinx-theme; extra == 'docs'
Requires-Dist: sphinx-codeautolink; extra == 'docs'
Requires-Dist: sphinx-copybutton; extra == 'docs'
Requires-Dist: sphinx-design; extra == 'docs'
Requires-Dist: sphinx-notfound-page; extra == 'docs'
Requires-Dist: sphinx-sitemap; extra == 'docs'
Requires-Dist: sphinx>=5; extra == 'docs'
Requires-Dist: sphinxcontrib-bibtex; extra == 'docs'
Requires-Dist: watermark; extra == 'docs'
